dlacorals/__init__.py
dlacorals/cs_measures.py
dlacorals/dla_model.py
dlacorals/dla_simulation.py
dlacorals/vis_tools.py
dlacorals-2024.0.1.dist-info/LICENSE
dlacorals-2024.0.1.dist-info/METADATA
dlacorals-2024.0.1.dist-info/WHEEL
dlacorals-2024.0.1.dist-info/top_level.txt
dlacorals-2024.0.1.dist-info/RECORD
