Metadata-Version: 2.1
Name: dlacorals
Version: 2024.0.1
Summary: DLA model for simulating coral growth
Author-email: Boyan Mihaylov <mboyo@duck.com>, Loes Bijman <loesbijman@gmail.com>, Esther Bakels <esther.bakels@gmail.com>, Aleksander Jacimovic <a.s.jacimovic@gmail.com>
Project-URL: Homepage, https://github.com/mboyan/complex-system-simulation
Project-URL: Issues, https://github.com/mboyan/complex-system-simulation/issues
Keywords: DLA,diffusion limited aggregation,corals,complex system,fractal
Classifier: Programming Language :: Python :: 3
Classifier: License :: OSI Approved :: MIT License
Classifier: Operating System :: OS Independent
Requires-Python: >=3.6
License-File: LICENSE
